lunrclient/__init__.py
lunrclient/base.py
lunrclient/client.py
lunrclient/displayable.py
lunrclient/lunr.py
lunrclient/lunr_shell.py
lunrclient/shared.py
lunrclient/storage.py
lunrclient/storage_shell.py
lunrclient/subcommand.py
lunrclient/tools.py
lunrclient/version.py
python_lunrclient-1.3.1.dist-info/DESCRIPTION.rst
python_lunrclient-1.3.1.dist-info/METADATA
python_lunrclient-1.3.1.dist-info/RECORD
python_lunrclient-1.3.1.dist-info/WHEEL
python_lunrclient-1.3.1.dist-info/entry_points.txt
python_lunrclient-1.3.1.dist-info/metadata.json
python_lunrclient-1.3.1.dist-info/pbr.json
python_lunrclient-1.3.1.dist-info/top_level.txt
