Metadata-Version: 2.0
Name: python-lunrclient
Version: 1.3.1
Summary: Lunr API client
Home-page: https://github.com/rackerlabs/python-lunrclient
Author: Derrick J Wippler
Author-email: thrawn01@gmail.com
License: UNKNOWN
Platform: UNKNOWN
Classifier: Environment :: Other Environment
Classifier: Intended Audience :: Information Technology
Classifier: Intended Audience :: System Administrators
Classifier: License :: OSI Approved :: Apache Software License
Classifier: Operating System :: POSIX :: Linux
Classifier: Programming Language :: Python
Classifier: Programming Language :: Python :: 2
Classifier: Programming Language :: Python :: 2.7
Requires-Dist: prettytable (>=0.7)
Requires-Dist: requests (>=2.9.1)
Requires-Dist: requests-mock (>=0.7.0)
Requires-Dist: six (>=1.10.0)
